MANIFEST.in
setup.cfg
setup.py
motorengine/__init__.py
motorengine/connection.py
motorengine/database.py
motorengine/document.py
motorengine/errors.py
motorengine/metaclasses.py
motorengine/queryset.py
motorengine/utils.py
motorengine/aggregation/__init__.py
motorengine/aggregation/avg.py
motorengine/aggregation/base.py
motorengine/aggregation/sum.py
motorengine/fields/__init__.py
motorengine/fields/base_field.py
motorengine/fields/binary_field.py
motorengine/fields/boolean_field.py
motorengine/fields/datetime_field.py
motorengine/fields/decimal_field.py
motorengine/fields/dynamic_field.py
motorengine/fields/email_field.py
motorengine/fields/embedded_document_field.py
motorengine/fields/float_field.py
motorengine/fields/int_field.py
motorengine/fields/json_field.py
motorengine/fields/list_field.py
motorengine/fields/reference_field.py
motorengine/fields/string_field.py
motorengine/fields/url_field.py
motorengine/fields/uuid_field.py
motorengine/query/__init__.py
motorengine/query/base.py
motorengine/query/exists.py
motorengine/query/greater_than.py
motorengine/query/greater_than_or_equal.py
motorengine/query/in_operator.py
motorengine/query/is_null.py
motorengine/query/lesser_than.py
motorengine/query/lesser_than_or_equal.py
motorengine/query/not_equal.py
motorengine/query/not_operator.py
motorengine/query/regx.py
motorengine/query_builder/__init__.py
motorengine/query_builder/field_list.py
motorengine/query_builder/node.py
motorengine/query_builder/transform.py